{
    "okalouti": {
        "awscloudformation": {
            "AuthRoleName": "cc7-cyan-20190317144439-authRole",
            "UnauthRoleArn": "arn:aws:iam::812245489460:role/cc7-cyan-20190317144439-unauthRole",
            "AuthRoleArn": "arn:aws:iam::812245489460:role/cc7-cyan-20190317144439-authRole",
            "Region": "ap-northeast-1",
            "DeploymentBucketName": "cc7-cyan-20190317144439-deployment",
            "UnauthRoleName": "cc7-cyan-20190317144439-unauthRole",
            "StackName": "cc7-cyan-20190317144439",
            "StackId": "arn:aws:cloudformation:ap-northeast-1:812245489460:stack/cc7-cyan-20190317144439/c1a20640-4877-11e9-8aff-068e2b92c6b0"
        },
        "categories": {
            "auth": {
                "cognito0dcc7d9e": {}
            }
        }
    }
}